croexp/__init__.py
croexp/vifcroexp.py
croexp-0.0.1.dist-info/METADATA
croexp-0.0.1.dist-info/WHEEL
croexp-0.0.1.dist-info/top_level.txt
croexp-0.0.1.dist-info/RECORD
