Metadata-Version: 2.1
Name: croexp
Version: 0.0.1
Summary: A package that allows to verify the parameters of a crontab expression.
Home-page: UNKNOWN
Author: Youn99 (Youness Kazize)
Author-email: <younny7kaziz@gmail.com>
License: UNKNOWN
Keywords: python,crontab expression
Platform: UNKNOWN
Classifier: Development Status :: 5 - Production/Stable
Classifier: Intended Audience :: Developers
Classifier: Programming Language :: Python :: 3
Classifier: Operating System :: Unix
Classifier: Operating System :: MacOS :: MacOS X
Classifier: Operating System :: Microsoft :: Windows
Requires-Dist: regex
